debugActivity/__init__.py
debugActivity/main.py
debugActivity/apksigner/__init__.py
debugActivity/apksigner/apksigner.jar
debugActivity/apksigner/pareto.jks
debugActivity/lldbtools/__init__.py
debugActivity/lldbtools/lldb-server
debugActivity/lldbtools/lldbtools.py
debugactivity-1.0.11.dist-info/METADATA
debugactivity-1.0.11.dist-info/WHEEL
debugactivity-1.0.11.dist-info/entry_points.txt
debugactivity-1.0.11.dist-info/top_level.txt
debugactivity-1.0.11.dist-info/RECORD
