Metadata-Version: 2.2
Name: debugActivity
Version: 1.0.11
Summary: use for jdb to debug android app
Author: pareto
License: MIT
Keywords: Android Debug Activity
Dynamic: author
Dynamic: description
Dynamic: description-content-type
Dynamic: keywords
Dynamic: license
Dynamic: summary
